re2.py
_re2.cpython-39-x86_64-linux-gnu.so
built_google_re2-0.0.7.20210224100510.dist-info/top_level.txt
built_google_re2-0.0.7.20210224100510.dist-info/RECORD
built_google_re2-0.0.7.20210224100510.dist-info/METADATA
built_google_re2-0.0.7.20210224100510.dist-info/WHEEL
